aliyun/__init__.py
aliyun/api/__init__.py
aliyun/api/base.py
aliyun/api/rest/__init__.py
top/__init__.py
top/api/__init__.py
top/api/base.py
top/api/rest/AppipGetRequest.py
top/api/rest/AreasGetRequest.py
top/api/rest/FilesGetRequest.py
top/api/rest/HttpdnsGetRequest.py
top/api/rest/JuItemsSearchRequest.py
top/api/rest/KfcKeywordSearchRequest.py
top/api/rest/OpenuidChangeRequest.py
top/api/rest/OpenuidGetBymixnickRequest.py
top/api/rest/OpenuidGetBytradeRequest.py
top/api/rest/OpenuidGetRequest.py
top/api/rest/TbkActivityInfoGetRequest.py
top/api/rest/TbkCouponConvertRequest.py
top/api/rest/TbkCouponGetRequest.py
top/api/rest/TbkDgItemCouponGetRequest.py
top/api/rest/TbkDgMaterialOptionalRequest.py
top/api/rest/TbkDgNewuserOrderGetRequest.py
top/api/rest/TbkDgNewuserOrderSumRequest.py
top/api/rest/TbkDgOptimusMaterialRequest.py
top/api/rest/TbkDgOptimusPromotionRequest.py
top/api/rest/TbkDgPunishOrderGetRequest.py
top/api/rest/TbkDgVegasSendStatusRequest.py
top/api/rest/TbkDgVegasTljCreateRequest.py
top/api/rest/TbkDgVegasTljInstanceReportRequest.py
top/api/rest/TbkItemConvertRequest.py
top/api/rest/TbkItemGetRequest.py
top/api/rest/TbkItemInfoGetRequest.py
top/api/rest/TbkItemRecommendGetRequest.py
top/api/rest/TbkJuTqgGetRequest.py
top/api/rest/TbkOrderDetailsGetRequest.py
top/api/rest/TbkOrderGetRequest.py
top/api/rest/TbkRelationRefundRequest.py
top/api/rest/TbkScInvitecodeGetRequest.py
top/api/rest/TbkScMaterialOptionalRequest.py
top/api/rest/TbkScNewuserOrderGetRequest.py
top/api/rest/TbkScNewuserOrderSumRequest.py
top/api/rest/TbkScOptimusMaterialRequest.py
top/api/rest/TbkScPublisherInfoGetRequest.py
top/api/rest/TbkScPublisherInfoSaveRequest.py
top/api/rest/TbkShopConvertRequest.py
top/api/rest/TbkShopGetRequest.py
top/api/rest/TbkShopRecommendGetRequest.py
top/api/rest/TbkSpreadGetRequest.py
top/api/rest/TbkTpwdConvertRequest.py
top/api/rest/TbkTpwdCreateRequest.py
top/api/rest/TbkUatmEventGetRequest.py
top/api/rest/TbkUatmEventItemGetRequest.py
topsdk-20.4.21.40.dist-info/LICENSE
topsdk-20.4.21.40.dist-info/METADATA
topsdk-20.4.21.40.dist-info/WHEEL
topsdk-20.4.21.40.dist-info/top_level.txt
topsdk-20.4.21.40.dist-info/RECORD
