Metadata-Version: 2.1
Name: topsdk
Version: 20.4.21.40
Summary: 淘宝联盟topsdk-淘宝返现工具
Home-page: UNKNOWN
Author: top
Author-email: play4fun@foxmail.com
License: MIT
Platform: UNKNOWN
